{
  "shared_zone_boundaries": [
    {
      "t_start": 199,
      "t_end": 196
    },
    {
      "t_start": 195,
      "t_end": 188
    },
    {
      "t_start": 187,
      "t_end": 183
    },
    {
      "t_start": 182,
      "t_end": 179
    },
    {
      "t_start": 178,
      "t_end": 174
    },
    {
      "t_start": 173,
      "t_end": 158
    },
    {
      "t_start": 157,
      "t_end": 154
    },
    {
      "t_start": 153,
      "t_end": 150
    },
    {
      "t_start": 149,
      "t_end": 146
    },
    {
      "t_start": 145,
      "t_end": 87
    },
    {
      "t_start": 86,
      "t_end": 82
    },
    {
      "t_start": 81,
      "t_end": 67
    },
    {
      "t_start": 66,
      "t_end": 62
    },
    {
      "t_start": 61,
      "t_end": 7
    },
    {
      "t_start": 6,
      "t_end": 5
    },
    {
      "t_start": 4,
      "t_end": 3
    },
    {
      "t_start": 2,
      "t_end": 0
    }
  ],
  "per_block": [
    {
      "block_id": 0,
      "k_per_zone": [
        4,
        4,
        3,
        4,
        3,
        4,
        4,
        4,
        4,
        4,
        3,
        4,
        3,
        4,
        2,
        2,
        3
      ],
      "num_F": 55,
      "num_R": 145,
      "total_cost_J_sum_zones": 5.458782742681048
    },
    {
      "block_id": 1,
      "k_per_zone": [
        4,
        4,
        3,
        4,
        3,
        4,
        4,
        4,
        4,
        4,
        3,
        4,
        3,
        4,
        2,
        2,
        3
      ],
      "num_F": 55,
      "num_R": 145,
      "total_cost_J_sum_zones": 5.458782742681048
    },
    {
      "block_id": 2,
      "k_per_zone": [
        4,
        4,
        3,
        4,
        3,
        4,
        4,
        4,
        4,
        4,
        3,
        4,
        3,
        4,
        2,
        2,
        3
      ],
      "num_F": 55,
      "num_R": 145,
      "total_cost_J_sum_zones": 5.458782742681048
    },
    {
      "block_id": 3,
      "k_per_zone": [
        4,
        4,
        3,
        4,
        4,
        4,
        4,
        4,
        4,
        4,
        3,
        4,
        4,
        4,
        2,
        2,
        3
      ],
      "num_F": 55,
      "num_R": 145,
      "total_cost_J_sum_zones": 5.460590250946138
    },
    {
      "block_id": 4,
      "k_per_zone": [
        4,
        4,
        3,
        4,
        4,
        4,
        4,
        4,
        4,
        4,
        3,
        4,
        3,
        4,
        2,
        2,
        3
      ],
      "num_F": 55,
      "num_R": 145,
      "total_cost_J_sum_zones": 5.636479027863226
    },
    {
      "block_id": 5,
      "k_per_zone": [
        4,
        4,
        3,
        4,
        4,
        4,
        4,
        4,
        4,
        4,
        3,
        4,
        4,
        4,
        2,
        2,
        3
      ],
      "num_F": 55,
      "num_R": 145,
      "total_cost_J_sum_zones": 5.612933520729816
    },
    {
      "block_id": 6,
      "k_per_zone": [
        4,
        4,
        4,
        4,
        4,
        4,
        4,
        4,
        4,
        4,
        4,
        4,
        4,
        4,
        2,
        2,
        3
      ],
      "num_F": 55,
      "num_R": 145,
      "total_cost_J_sum_zones": 5.561029729953791
    },
    {
      "block_id": 7,
      "k_per_zone": [
        4,
        4,
        3,
        4,
        3,
        4,
        4,
        4,
        4,
        4,
        3,
        4,
        3,
        4,
        2,
        2,
        3
      ],
      "num_F": 55,
      "num_R": 145,
      "total_cost_J_sum_zones": 5.458782742681048
    },
    {
      "block_id": 8,
      "k_per_zone": [
        4,
        4,
        3,
        4,
        3,
        4,
        4,
        4,
        4,
        4,
        3,
        4,
        3,
        4,
        2,
        2,
        3
      ],
      "num_F": 55,
      "num_R": 145,
      "total_cost_J_sum_zones": 5.458782742681048
    },
    {
      "block_id": 9,
      "k_per_zone": [
        4,
        4,
        4,
        4,
        4,
        4,
        4,
        4,
        4,
        4,
        4,
        4,
        3,
        4,
        2,
        2,
        3
      ],
      "num_F": 55,
      "num_R": 145,
      "total_cost_J_sum_zones": 5.5468148220851505
    },
    {
      "block_id": 10,
      "k_per_zone": [
        4,
        4,
        4,
        4,
        4,
        4,
        4,
        4,
        4,
        4,
        4,
        4,
        3,
        4,
        2,
        2,
        3
      ],
      "num_F": 55,
      "num_R": 145,
      "total_cost_J_sum_zones": 5.582157361193591
    },
    {
      "block_id": 11,
      "k_per_zone": [
        4,
        4,
        4,
        4,
        4,
        4,
        4,
        4,
        4,
        4,
        4,
        4,
        3,
        4,
        2,
        2,
        3
      ],
      "num_F": 55,
      "num_R": 145,
      "total_cost_J_sum_zones": 5.637004319302522
    },
    {
      "block_id": 12,
      "k_per_zone": [
        4,
        4,
        4,
        4,
        3,
        4,
        4,
        4,
        4,
        4,
        3,
        4,
        4,
        4,
        2,
        2,
        3
      ],
      "num_F": 55,
      "num_R": 145,
      "total_cost_J_sum_zones": 5.565391298357025
    },
    {
      "block_id": 13,
      "k_per_zone": [
        4,
        4,
        4,
        4,
        4,
        4,
        4,
        4,
        4,
        4,
        3,
        4,
        3,
        4,
        2,
        2,
        3
      ],
      "num_F": 55,
      "num_R": 145,
      "total_cost_J_sum_zones": 6.1021683394827555
    },
    {
      "block_id": 14,
      "k_per_zone": [
        4,
        4,
        4,
        4,
        4,
        4,
        4,
        4,
        4,
        4,
        4,
        4,
        3,
        4,
        2,
        2,
        3
      ],
      "num_F": 55,
      "num_R": 145,
      "total_cost_J_sum_zones": 5.591948689176812
    },
    {
      "block_id": 15,
      "k_per_zone": [
        4,
        4,
        4,
        4,
        4,
        4,
        4,
        4,
        4,
        4,
        4,
        4,
        3,
        4,
        2,
        2,
        3
      ],
      "num_F": 55,
      "num_R": 145,
      "total_cost_J_sum_zones": 5.867774498480103
    },
    {
      "block_id": 16,
      "k_per_zone": [
        4,
        4,
        3,
        4,
        4,
        4,
        4,
        4,
        4,
        4,
        4,
        4,
        3,
        4,
        2,
        2,
        2
      ],
      "num_F": 56,
      "num_R": 144,
      "total_cost_J_sum_zones": 6.299739720891206
    },
    {
      "block_id": 17,
      "k_per_zone": [
        4,
        4,
        3,
        4,
        3,
        4,
        4,
        4,
        4,
        4,
        3,
        4,
        3,
        4,
        2,
        2,
        3
      ],
      "num_F": 55,
      "num_R": 145,
      "total_cost_J_sum_zones": 5.458782742681048
    },
    {
      "block_id": 18,
      "k_per_zone": [
        4,
        4,
        3,
        4,
        3,
        4,
        4,
        4,
        4,
        4,
        3,
        4,
        3,
        4,
        2,
        2,
        3
      ],
      "num_F": 55,
      "num_R": 145,
      "total_cost_J_sum_zones": 5.458782742681048
    },
    {
      "block_id": 19,
      "k_per_zone": [
        4,
        4,
        4,
        4,
        4,
        4,
        4,
        4,
        4,
        4,
        3,
        4,
        3,
        4,
        2,
        2,
        3
      ],
      "num_F": 55,
      "num_R": 145,
      "total_cost_J_sum_zones": 5.591221377400162
    },
    {
      "block_id": 20,
      "k_per_zone": [
        4,
        4,
        4,
        4,
        4,
        4,
        4,
        4,
        4,
        4,
        3,
        4,
        3,
        4,
        2,
        2,
        3
      ],
      "num_F": 55,
      "num_R": 145,
      "total_cost_J_sum_zones": 5.72244568658149
    },
    {
      "block_id": 21,
      "k_per_zone": [
        4,
        4,
        4,
        4,
        4,
        4,
        4,
        4,
        4,
        4,
        3,
        4,
        4,
        4,
        2,
        2,
        3
      ],
      "num_F": 55,
      "num_R": 145,
      "total_cost_J_sum_zones": 5.493468079077016
    },
    {
      "block_id": 22,
      "k_per_zone": [
        4,
        4,
        4,
        4,
        4,
        4,
        4,
        4,
        4,
        4,
        3,
        4,
        3,
        4,
        2,
        2,
        3
      ],
      "num_F": 55,
      "num_R": 145,
      "total_cost_J_sum_zones": 5.764201916095305
    },
    {
      "block_id": 23,
      "k_per_zone": [
        4,
        4,
        4,
        4,
        3,
        4,
        4,
        4,
        4,
        4,
        4,
        4,
        3,
        4,
        2,
        2,
        3
      ],
      "num_F": 55,
      "num_R": 145,
      "total_cost_J_sum_zones": 5.530848318855973
    },
    {
      "block_id": 24,
      "k_per_zone": [
        4,
        4,
        3,
        4,
        4,
        4,
        4,
        4,
        4,
        4,
        4,
        4,
        3,
        4,
        2,
        2,
        3
      ],
      "num_F": 55,
      "num_R": 145,
      "total_cost_J_sum_zones": 5.904612588058788
    }
  ],
  "per_zone": [
    {
      "zone_id": 0,
      "length": 4,
      "candidate_k": [
        1,
        2,
        3,
        4
      ],
      "selected_k_per_block": [
        4,
        4,
        4,
        4,
        4,
        4,
        4,
        4,
        4,
        4,
        4,
        4,
        4,
        4,
        4,
        4,
        4,
        4,
        4,
        4,
        4,
        4,
        4,
        4,
        4
      ],
      "selected_J_per_block": [
        0.25,
        0.25,
        0.25,
        0.25004105741226096,
        0.2514704987988302,
        0.25183092684220487,
        0.25116903374037186,
        0.25,
        0.25,
        0.2525909698057078,
        0.25311951241668745,
        0.25336894725860065,
        0.25209450523844357,
        0.2599301964005952,
        0.2518144016368119,
        0.252469802874228,
        0.2513063980170854,
        0.25,
        0.25,
        0.25407125113728724,
        0.25822354411411197,
        0.2509093376796174,
        0.2560040507632409,
        0.2514795838571017,
        0.2556134783242467
      ],
      "cost_table_ref": "scheduler_diagnostics.json -> cost_tables_per_zone[0]"
    },
    {
      "zone_id": 1,
      "length": 8,
      "candidate_k": [
        1,
        2,
        3,
        4
      ],
      "selected_k_per_block": [
        4,
        4,
        4,
        4,
        4,
        4,
        4,
        4,
        4,
        4,
        4,
        4,
        4,
        4,
        4,
        4,
        4,
        4,
        4,
        4,
        4,
        4,
        4,
        4,
        4
      ],
      "selected_J_per_block": [
        0.25,
        0.25,
        0.25,
        0.25008650674294125,
        0.251848265710263,
        0.25229219710707446,
        0.251369968324779,
        0.25,
        0.25,
        0.25408468672846046,
        0.2557093399717285,
        0.2571197391402032,
        0.25452768191132863,
        0.2771145329920514,
        0.2552265476445442,
        0.25403356785473974,
        0.25675038105902165,
        0.25,
        0.25,
        0.2584155571492151,
        0.2750050402515756,
        0.25313180446111705,
        0.26265440024878023,
        0.2530657769180252,
        0.2625849923238598
      ],
      "cost_table_ref": "scheduler_diagnostics.json -> cost_tables_per_zone[1]"
    },
    {
      "zone_id": 2,
      "length": 5,
      "candidate_k": [
        1,
        2,
        3,
        4
      ],
      "selected_k_per_block": [
        3,
        3,
        3,
        3,
        3,
        3,
        4,
        3,
        3,
        4,
        4,
        4,
        4,
        4,
        4,
        4,
        3,
        3,
        3,
        4,
        4,
        4,
        4,
        4,
        3
      ],
      "selected_J_per_block": [
        0.4,
        0.4,
        0.4,
        0.40008435622753946,
        0.4013834042546207,
        0.4016533125464585,
        0.4011512805524607,
        0.4,
        0.4,
        0.40413899192553043,
        0.4072230633207715,
        0.4084755254964705,
        0.40565946520777657,
        0.42639040249892507,
        0.40362661357141244,
        0.4038486453205088,
        0.4070948448602293,
        0.4,
        0.4,
        0.4082407657565006,
        0.41796801346512075,
        0.4013838352284034,
        0.41088001112535466,
        0.4017242640670048,
        0.43435528599139717
      ],
      "cost_table_ref": "scheduler_diagnostics.json -> cost_tables_per_zone[2]"
    },
    {
      "zone_id": 3,
      "length": 4,
      "candidate_k": [
        1,
        2,
        3,
        4
      ],
      "selected_k_per_block": [
        4,
        4,
        4,
        4,
        4,
        4,
        4,
        4,
        4,
        4,
        4,
        4,
        4,
        4,
        4,
        4,
        4,
        4,
        4,
        4,
        4,
        4,
        4,
        4,
        4
      ],
      "selected_J_per_block": [
        0.25,
        0.25,
        0.25,
        0.25010999176089904,
        0.2529489154833141,
        0.25277728601595373,
        0.2517755148381172,
        0.25,
        0.25,
        0.25631912262489315,
        0.2590405279424678,
        0.2613523215429348,
        0.25777439528608087,
        0.2787351141319765,
        0.2568400369175987,
        0.2545534829002801,
        0.2538208789506522,
        0.25,
        0.25,
        0.26343341324302355,
        0.2705292169852879,
        0.25250064065479716,
        0.2641167022227969,
        0.25328178225098946,
        0.2597834965207666
      ],
      "cost_table_ref": "scheduler_diagnostics.json -> cost_tables_per_zone[3]"
    },
    {
      "zone_id": 4,
      "length": 5,
      "candidate_k": [
        1,
        2,
        3,
        4
      ],
      "selected_k_per_block": [
        3,
        3,
        3,
        4,
        4,
        4,
        4,
        3,
        3,
        4,
        4,
        4,
        3,
        4,
        4,
        4,
        4,
        3,
        3,
        4,
        4,
        4,
        4,
        3,
        4
      ],
      "selected_J_per_block": [
        0.4,
        0.4,
        0.4,
        0.40010898389502225,
        0.4040781183336734,
        0.4029772684713073,
        0.40189685181564444,
        0.4,
        0.4,
        0.40812080682686,
        0.4101331701424573,
        0.4149608365198739,
        0.4074729403612738,
        0.436023588144714,
        0.4077538085517317,
        0.43557692390195474,
        0.40411009427384775,
        0.4,
        0.4,
        0.4132969005964929,
        0.4209025143299528,
        0.4030816954187678,
        0.41459054890088165,
        0.4041490420336509,
        0.4195456269735264
      ],
      "cost_table_ref": "scheduler_diagnostics.json -> cost_tables_per_zone[4]"
    },
    {
      "zone_id": 5,
      "length": 16,
      "candidate_k": [
        1,
        2,
        3,
        4
      ],
      "selected_k_per_block": [
        4,
        4,
        4,
        4,
        4,
        4,
        4,
        4,
        4,
        4,
        4,
        4,
        4,
        4,
        4,
        4,
        4,
        4,
        4,
        4,
        4,
        4,
        4,
        4,
        4
      ],
      "selected_J_per_block": [
        0.25,
        0.25,
        0.25,
        0.2501410111534528,
        0.2551673868685931,
        0.25576869454701756,
        0.2538873036762114,
        0.25,
        0.25,
        0.2584260104446523,
        0.26082423405724875,
        0.2647514312783668,
        0.25766258205722337,
        0.28666587047208153,
        0.2590302959170525,
        0.26157757735339066,
        0.2626064793584899,
        0.25,
        0.25,
        0.2638775798081541,
        0.2761290828898849,
        0.2529681869013706,
        0.27319863262688504,
        0.2555121614013395,
        0.27123667061645795
      ],
      "cost_table_ref": "scheduler_diagnostics.json -> cost_tables_per_zone[5]"
    },
    {
      "zone_id": 6,
      "length": 4,
      "candidate_k": [
        1,
        2,
        3,
        4
      ],
      "selected_k_per_block": [
        4,
        4,
        4,
        4,
        4,
        4,
        4,
        4,
        4,
        4,
        4,
        4,
        4,
        4,
        4,
        4,
        4,
        4,
        4,
        4,
        4,
        4,
        4,
        4,
        4
      ],
      "selected_J_per_block": [
        0.25,
        0.25,
        0.25,
        0.25009591243997775,
        0.254850648057844,
        0.25741113244346403,
        0.2542362321223428,
        0.25,
        0.25,
        0.256941935473781,
        0.2582397782825889,
        0.2614318661122558,
        0.25712335893759525,
        0.2802854725338822,
        0.2567868353252128,
        0.29835775722421987,
        0.28787875212243913,
        0.25,
        0.25,
        0.25770754056030476,
        0.26710069401207237,
        0.2526734438710008,
        0.27640995375584715,
        0.2561353181127616,
        0.2745465213122467
      ],
      "cost_table_ref": "scheduler_diagnostics.json -> cost_tables_per_zone[6]"
    },
    {
      "zone_id": 7,
      "length": 4,
      "candidate_k": [
        1,
        2,
        3,
        4
      ],
      "selected_k_per_block": [
        4,
        4,
        4,
        4,
        4,
        4,
        4,
        4,
        4,
        4,
        4,
        4,
        4,
        4,
        4,
        4,
        4,
        4,
        4,
        4,
        4,
        4,
        4,
        4,
        4
      ],
      "selected_J_per_block": [
        0.25,
        0.25,
        0.25,
        0.2501364451259915,
        0.25514746088700224,
        0.25680416032710324,
        0.2545838724419103,
        0.25,
        0.25,
        0.2558715082774817,
        0.25878287504167946,
        0.2601294024396958,
        0.2581832787272556,
        0.2941210484727711,
        0.2582821277463204,
        0.2637473186101876,
        0.28032508541331885,
        0.25,
        0.25,
        0.2589103912840437,
        0.2741887510178485,
        0.2528681064916348,
        0.2790178315753313,
        0.2571769345621498,
        0.2769752548541874
      ],
      "cost_table_ref": "scheduler_diagnostics.json -> cost_tables_per_zone[7]"
    },
    {
      "zone_id": 8,
      "length": 4,
      "candidate_k": [
        1,
        2,
        3,
        4
      ],
      "selected_k_per_block": [
        4,
        4,
        4,
        4,
        4,
        4,
        4,
        4,
        4,
        4,
        4,
        4,
        4,
        4,
        4,
        4,
        4,
        4,
        4,
        4,
        4,
        4,
        4,
        4,
        4
      ],
      "selected_J_per_block": [
        0.25,
        0.25,
        0.25,
        0.25014445305110217,
        0.2550233395208871,
        0.25688182856607344,
        0.25843802947170724,
        0.25,
        0.25,
        0.256501422546902,
        0.2575296229454601,
        0.26078267193452903,
        0.25779401505665706,
        0.2946242325324455,
        0.26067642919002687,
        0.26562856330364837,
        0.3234721785045824,
        0.25,
        0.25,
        0.258624720040255,
        0.2666879628447123,
        0.2533226512112386,
        0.26993792156809054,
        0.25473170343747836,
        0.3237280268377314
      ],
      "cost_table_ref": "scheduler_diagnostics.json -> cost_tables_per_zone[8]"
    },
    {
      "zone_id": 9,
      "length": 59,
      "candidate_k": [
        1,
        2,
        3,
        4
      ],
      "selected_k_per_block": [
        4,
        4,
        4,
        4,
        4,
        4,
        4,
        4,
        4,
        4,
        4,
        4,
        4,
        4,
        4,
        4,
        4,
        4,
        4,
        4,
        4,
        4,
        4,
        4,
        4
      ],
      "selected_J_per_block": [
        0.2542372881355932,
        0.2542372881355932,
        0.2542372881355932,
        0.2543659635762173,
        0.2610202158271583,
        0.2628681858109629,
        0.25942593100022676,
        0.2542372881355932,
        0.2542372881355932,
        0.2595598698664097,
        0.26202244789814505,
        0.2669559100374002,
        0.2618531843525642,
        0.30203837196981803,
        0.2661276545679531,
        0.2697091892187272,
        0.27137118508945446,
        0.2542372881355932,
        0.2542372881355932,
        0.2630123685169562,
        0.2697241351854599,
        0.2559288463361549,
        0.2717340980170335,
        0.2577304669188731,
        0.2756541940116143
      ],
      "cost_table_ref": "scheduler_diagnostics.json -> cost_tables_per_zone[9]"
    },
    {
      "zone_id": 10,
      "length": 5,
      "candidate_k": [
        1,
        2,
        3,
        4
      ],
      "selected_k_per_block": [
        3,
        3,
        3,
        3,
        3,
        3,
        4,
        3,
        3,
        4,
        4,
        4,
        3,
        3,
        4,
        4,
        4,
        3,
        3,
        3,
        3,
        3,
        3,
        4,
        4
      ],
      "selected_J_per_block": [
        0.4,
        0.4,
        0.4,
        0.40012038264940536,
        0.40458907798748206,
        0.40502820928367816,
        0.4029392260160125,
        0.4,
        0.4,
        0.4030718521499622,
        0.4082313258612733,
        0.40779076900637073,
        0.4049694439487897,
        0.4303358553322098,
        0.405881005572638,
        0.4465437368953514,
        0.40883220361028283,
        0.4,
        0.4,
        0.4046970485329087,
        0.40805728900907895,
        0.4008452801612334,
        0.4084814953109687,
        0.40151664755933014,
        0.4090661050627629
      ],
      "cost_table_ref": "scheduler_diagnostics.json -> cost_tables_per_zone[10]"
    },
    {
      "zone_id": 11,
      "length": 15,
      "candidate_k": [
        1,
        2,
        3,
        4
      ],
      "selected_k_per_block": [
        4,
        4,
        4,
        4,
        4,
        4,
        4,
        4,
        4,
        4,
        4,
        4,
        4,
        4,
        4,
        4,
        4,
        4,
        4,
        4,
        4,
        4,
        4,
        4,
        4
      ],
      "selected_J_per_block": [
        0.26666666666666666,
        0.26666666666666666,
        0.26666666666666666,
        0.26674506411436183,
        0.2725502555276581,
        0.27438811897263893,
        0.2706531941863968,
        0.26666666666666666,
        0.26666666666666666,
        0.27045418097379875,
        0.2716200273763105,
        0.27576843820680785,
        0.27146310633772003,
        0.3063250274128384,
        0.27522025206967915,
        0.27548398941725555,
        0.2813828797962655,
        0.26666666666666666,
        0.26666666666666666,
        0.27169423596816794,
        0.27703962204994087,
        0.26780116611068905,
        0.27589078478421936,
        0.2683514009824506,
        0.2824114567862341
      ],
      "cost_table_ref": "scheduler_diagnostics.json -> cost_tables_per_zone[11]"
    },
    {
      "zone_id": 12,
      "length": 5,
      "candidate_k": [
        1,
        2,
        3,
        4
      ],
      "selected_k_per_block": [
        3,
        3,
        3,
        4,
        3,
        4,
        4,
        3,
        3,
        3,
        3,
        3,
        4,
        3,
        3,
        3,
        3,
        3,
        3,
        3,
        3,
        4,
        3,
        3,
        3
      ],
      "selected_J_per_block": [
        0.4,
        0.4,
        0.4,
        0.4000542222870111,
        0.40553529061900967,
        0.40674382943850035,
        0.4032038543513919,
        0.4,
        0.4,
        0.40230960208167144,
        0.40332802923271044,
        0.4054086416275367,
        0.40307573016470455,
        0.4272781664437673,
        0.4043457699546693,
        0.4373242634814987,
        0.418676422474285,
        0.4,
        0.4,
        0.4065778245215026,
        0.4058483552436809,
        0.4006603931725391,
        0.4061533780933563,
        0.4012268638849657,
        0.4071957480364169
      ],
      "cost_table_ref": "scheduler_diagnostics.json -> cost_tables_per_zone[12]"
    },
    {
      "zone_id": 13,
      "length": 55,
      "candidate_k": [
        1,
        2,
        3,
        4
      ],
      "selected_k_per_block": [
        4,
        4,
        4,
        4,
        4,
        4,
        4,
        4,
        4,
        4,
        4,
        4,
        4,
        4,
        4,
        4,
        4,
        4,
        4,
        4,
        4,
        4,
        4,
        4,
        4
      ],
      "selected_J_per_block": [
        0.2545454545454545,
        0.2545454545454545,
        0.2545454545454545,
        0.25459642848708247,
        0.26686203451320156,
        0.2652066166589349,
        0.25915637736744995,
        0.2545454545454545,
        0.2545454545454545,
        0.25688794603393417,
        0.25773574732007215,
        0.2598280133155863,
        0.25739088028005136,
        0.27496509138930175,
        0.25877780273214124,
        0.26396305293005184,
        0.27211352436803277,
        0.2545454545454545,
        0.2545454545454545,
        0.2573631503110215,
        0.2599192436881311,
        0.25536559548513416,
        0.26383906822055864,
        0.25633109133425236,
        0.26956725507113855
      ],
      "cost_table_ref": "scheduler_diagnostics.json -> cost_tables_per_zone[13]"
    },
    {
      "zone_id": 14,
      "length": 2,
      "candidate_k": [
        1,
        2
      ],
      "selected_k_per_block": [
        2,
        2,
        2,
        2,
        2,
        2,
        2,
        2,
        2,
        2,
        2,
        2,
        2,
        2,
        2,
        2,
        2,
        2,
        2,
        2,
        2,
        2,
        2,
        2,
        2
      ],
      "selected_J_per_block": [
        0.5,
        0.5,
        0.5,
        0.5000567487188476,
        0.5145301847506288,
        0.513449363979688,
        0.5060717746045318,
        0.5,
        0.5,
        0.5021273428964408,
        0.5029502891709278,
        0.5046986787928229,
        0.5027145092146501,
        0.5216182167399648,
        0.5038619727538501,
        0.5175556804945581,
        0.5392963071664174,
        0.5,
        0.5,
        0.5022951771286174,
        0.5051145193454272,
        0.5008036806416536,
        0.5124503509833077,
        0.5026587641916819,
        0.5215362445968721
      ],
      "cost_table_ref": "scheduler_diagnostics.json -> cost_tables_per_zone[14]"
    },
    {
      "zone_id": 15,
      "length": 2,
      "candidate_k": [
        1,
        2
      ],
      "selected_k_per_block": [
        2,
        2,
        2,
        2,
        2,
        2,
        2,
        2,
        2,
        2,
        2,
        2,
        2,
        2,
        2,
        2,
        2,
        2,
        2,
        2,
        2,
        2,
        2,
        2,
        2
      ],
      "selected_J_per_block": [
        0.5,
        0.5,
        0.5,
        0.5000568312424053,
        0.5195275264535414,
        0.5142645709480795,
        0.5078950804783839,
        0.5,
        0.5,
        0.5027844577607921,
        0.5037713718545533,
        0.5056728030275257,
        0.5052454668403292,
        0.5330348719111501,
        0.5065518627023337,
        0.5262380169950911,
        0.61206636859311,
        0.5,
        0.5,
        0.5029406476009948,
        0.5068790407759397,
        0.5010607907814121,
        0.51330402525565,
        0.5034233121799514,
        0.5269116438925266
      ],
      "cost_table_ref": "scheduler_diagnostics.json -> cost_tables_per_zone[15]"
    },
    {
      "zone_id": 16,
      "length": 3,
      "candidate_k": [
        1,
        2,
        3
      ],
      "selected_k_per_block": [
        3,
        3,
        3,
        3,
        3,
        3,
        3,
        3,
        3,
        3,
        3,
        3,
        3,
        3,
        3,
        3,
        2,
        3,
        3,
        3,
        3,
        3,
        3,
        3,
        3
      ],
      "selected_J_per_block": [
        0.3333333333333333,
        0.3333333333333333,
        0.3333333333333333,
        0.3336458920616203,
        0.4099464042695187,
        0.3825878187706762,
        0.3731762049658531,
        0.3333333333333333,
        0.3333333333333333,
        0.3466241156678725,
        0.3518959983585075,
        0.36850832356554025,
        0.3503867544345813,
        0.4726822801042628,
        0.3611452723228359,
        0.4411629297044118,
        0.7686357372336917,
        0.3333333333333333,
        0.3333333333333333,
        0.34606280524471567,
        0.3631286613732646,
        0.33816262447025214,
        0.4055386626430026,
        0.3523532051639664,
        0.43390058684680194
      ],
      "cost_table_ref": "scheduler_diagnostics.json -> cost_tables_per_zone[16]"
    }
  ],
  "lambda_baseline": 1.0
}